gamezip64
