Metadata-Version: 2.1
Name: gamezip64
Version: 0.1.3
Summary: microbit Kitronik Game ZIP 64 plugin
Home-page: UNKNOWN
Author: Adam Jenca
Author-email: jenca.a@gjh.sk
License: UNKNOWN
Platform: UNKNOWN
